datalake_ingester/__init__.py
datalake_ingester/log.py
datalake_ingester/translator.py
datalake_ingester/ingester.py
datalake_ingester/errors.py
datalake_ingester/reporter.py
datalake_ingester/storage.py
datalake_ingester/cli.py
datalake_ingester/queue.py
datalake_ingester-0.5.0.dist-info/RECORD
datalake_ingester-0.5.0.dist-info/entry_points.txt
datalake_ingester-0.5.0.dist-info/METADATA
datalake_ingester-0.5.0.dist-info/DESCRIPTION.rst
datalake_ingester-0.5.0.dist-info/WHEEL
datalake_ingester-0.5.0.dist-info/top_level.txt
datalake_ingester-0.5.0.dist-info/metadata.json
