Metadata-Version: 2.0
Name: datalake-ingester
Version: 0.5.0
Summary: datalake_ingester ingests datalake metadata records
Home-page: https://github.com/planetlabs/datalake-ingester
Author: Brian Cavagnolo
Author-email: brian@planet.com
License: UNKNOWN
Platform: UNKNOWN
Requires-Dist: pyver (>=1.0.18)
Requires-Dist: boto (>=2.38.0)
Requires-Dist: configargparse (>=0.9.3)
Requires-Dist: memoized-property (>=1.0.2)
Requires-Dist: simplejson (>=3.3.1)
Requires-Dist: datalake-common (>=0.5)
Requires-Dist: raven (>=5.6.0)
Requires-Dist: click (>=5.1)
Provides-Extra: test
Requires-Dist: pytest (==2.7.2); extra == 'test'
Requires-Dist: pip (==7.1.0); extra == 'test'
Requires-Dist: wheel (==0.24.0); extra == 'test'
Requires-Dist: moto (==0.4.12); extra == 'test'
